poly_escape_graph
