Metadata-Version: 1.2
Name: poly-escape-graph
Version: 3.1
Summary: Python graph oriented micro services network in order to implement a scalable plugins architecture
Home-page: https://mjollnir.unice.fr/bitbucket/scm/pee/private.git
Author: PEE
Author-email: UNKNOWN
License: Unlicense
Platform: UNKNOWN
Requires-Python: >=3.6, <4
